pydca/__init__.py
pydca/main.py
pydca/config_dca/__init__.py
pydca/config_dca/config_log.py
pydca/contact_visualizer/__init__.py
pydca/contact_visualizer/contact_visualizer.py
pydca/dca_utilities/__init__.py
pydca/dca_utilities/dca_utilities.py
pydca/fasta_reader/__init__.py
pydca/fasta_reader/fasta_reader.py
pydca/meanfield_dca/__init__.py
pydca/meanfield_dca/meanfield_dca.py
pydca/meanfield_dca/msa_numerics.py
pydca/msa_trimmer/__init__.py
pydca/msa_trimmer/msa_trimmer.py
pydca/sequence_backmapper/__init__.py
pydca/sequence_backmapper/scoring_matrix.py
pydca/sequence_backmapper/sequence_backmapper.py
pydca-0.2.dist-info/LICENSE
pydca-0.2.dist-info/METADATA
pydca-0.2.dist-info/WHEEL
pydca-0.2.dist-info/entry_points.txt
pydca-0.2.dist-info/top_level.txt
pydca-0.2.dist-info/RECORD
