Metadata-Version: 2.1
Name: pydca
Version: 0.2
Summary: Direct couplings analysis (DCA) for protein and RNA sequences
Home-page: https://github.com/KIT-MBS/pydca
Author: Mehari B. Zerihun
Author-email: mbzerihun@gmail.com
License: UNKNOWN
Platform: UNKNOWN
Classifier: Programming Language :: Python :: 3
Classifier: License :: OSI Approved :: MIT License
Classifier: Operating System :: OS Independent
Classifier: Development Status :: 4 - Beta
Requires-Python: >=3.5
